super_ec2/__init__.py
super_ec2/py.typed
super_ec2/_jsii/__init__.py
super_ec2/_jsii/super-ec2@0.0.420.jsii.tgz
super_ec2-0.0.420.dist-info/LICENSE
super_ec2-0.0.420.dist-info/METADATA
super_ec2-0.0.420.dist-info/WHEEL
super_ec2-0.0.420.dist-info/top_level.txt
super_ec2-0.0.420.dist-info/RECORD
