Metadata-Version: 2.1
Name: super-ec2
Version: 0.0.420
Summary: A construct lib for AWS CDK EC2
Home-page: https://github.com/cdk-constructs-zone/super-ec2.git
Author: @cdk-constructs-zone
License: Apache-2.0
Project-URL: Source, https://github.com/cdk-constructs-zone/super-ec2.git
Classifier: Intended Audience :: Developers
Classifier: Operating System :: OS Independent
Classifier: Programming Language :: JavaScript
Classifier: Programming Language :: Python :: 3 :: Only
Classifier: Programming Language :: Python :: 3.7
Classifier: Programming Language :: Python :: 3.8
Classifier: Programming Language :: Python :: 3.9
Classifier: Programming Language :: Python :: 3.10
Classifier: Programming Language :: Python :: 3.11
Classifier: Typing :: Typed
Classifier: Development Status :: 4 - Beta
Classifier: License :: OSI Approved
Requires-Python: ~=3.7
License-File: LICENSE
Requires-Dist: aws-cdk.aws-autoscaling-hooktargets <2.0.0,>=1.171.0
Requires-Dist: aws-cdk.aws-autoscaling <2.0.0,>=1.171.0
Requires-Dist: aws-cdk.aws-certificatemanager <2.0.0,>=1.171.0
Requires-Dist: aws-cdk.aws-ec2 <2.0.0,>=1.171.0
Requires-Dist: aws-cdk.aws-elasticloadbalancingv2-targets <2.0.0,>=1.171.0
Requires-Dist: aws-cdk.aws-elasticloadbalancingv2 <2.0.0,>=1.171.0
Requires-Dist: aws-cdk.aws-iam <2.0.0,>=1.171.0
Requires-Dist: aws-cdk.aws-lambda <2.0.0,>=1.171.0
Requires-Dist: aws-cdk.aws-logs <2.0.0,>=1.171.0
Requires-Dist: aws-cdk.aws-route53-targets <2.0.0,>=1.171.0
Requires-Dist: aws-cdk.aws-route53 <2.0.0,>=1.171.0
Requires-Dist: aws-cdk.aws-s3-assets <2.0.0,>=1.171.0
Requires-Dist: aws-cdk.aws-s3 <2.0.0,>=1.171.0
Requires-Dist: aws-cdk.aws-sns-subscriptions <2.0.0,>=1.171.0
Requires-Dist: aws-cdk.aws-sns <2.0.0,>=1.171.0
Requires-Dist: aws-cdk.core <2.0.0,>=1.171.0
Requires-Dist: aws-cdk.custom-resources <2.0.0,>=1.171.0
Requires-Dist: constructs <4.0.0,>=3.2.27
Requires-Dist: jsii <2.0.0,>=1.89.0
Requires-Dist: publication >=0.0.3
Requires-Dist: typeguard ~=2.13.3
